marple/.coveragerc
marple/__init__.py
marple/__main__.py
marple/config.txt
marple/marple_setup
marple/pylintrc.txt
marple/test.py
marple/collect/__init__.py
marple/collect/main.py
marple/collect/interface/__init__.py
marple/collect/interface/collecter.py
marple/collect/interface/ebpf.py
marple/collect/interface/iosnoop.py
marple/collect/interface/perf.py
marple/collect/interface/smem.py
marple/collect/test/__init__.py
marple/collect/test/test_main.py
marple/collect/test/interface/__init__.py
marple/collect/test/interface/test_ebpf.py
marple/collect/test/interface/test_iosnoop.py
marple/collect/test/interface/test_perf.py
marple/collect/tools/__init__.py
marple/collect/tools/bcc-tools/__init__.py
marple/collect/tools/bcc-tools/mallocstacks.py
marple/collect/tools/bcc-tools/memleak.py
marple/collect/tools/bcc-tools/tcptracer
marple/collect/tools/perf-tools/LICENSE
marple/collect/tools/perf-tools/__init__.py
marple/collect/tools/perf-tools/iosnoop
marple/common/__init__.py
marple/common/config.py
marple/common/consts.py
marple/common/data_io.py
marple/common/exceptions.py
marple/common/file.py
marple/common/output.py
marple/common/paths.py
marple/common/util.py
marple/common/test/__init__.py
marple/common/test/example_scheddata.cpel
marple/common/test/test_data_io.py
marple/common/test/test_file.py
marple/display/__init__.py
marple/display/main.py
marple/display/tcpplotter.py
marple/display/interface/__init__.py
marple/display/interface/flamegraph.py
marple/display/interface/g2.py
marple/display/interface/generic_display.py
marple/display/interface/heatmap.py
marple/display/interface/stackplot.py
marple/display/interface/treemap.py
marple/display/test/__init__.py
marple/display/test/test_main.py
marple/display/test/interface/__init__.py
marple/display/test/interface/test_flamegraph.py
marple/display/test/interface/test_heatmap.py
marple/display/test/interface/test_treemap.py
marple/display/tools/__init__.py
marple-0.1.dev1.dist-info/METADATA
marple-0.1.dev1.dist-info/RECORD
marple-0.1.dev1.dist-info/WHEEL
marple-0.1.dev1.dist-info/entry_points.txt
marple-0.1.dev1.dist-info/top_level.txt
