Metadata-Version: 2.1
Name: marple
Version: 0.1.dev1
Summary: A Linux profiling multi-tool with visualisation.
Home-page: http://github.com/ensoft/marple/
Author: Ensoft Ltd
Author-email: ensoft@ensoft.co.uk
License: UNKNOWN
Project-URL: Source Code, http://github.com/ensoft/marple/
Project-URL: Automated testing, https://travis-ci.org/ensoft/marple/
Project-URL: Code coverage, https://codecov.io/gh/ensoft/marple/
Keywords: Linux profile profiling perf bcc visualisation
Platform: UNKNOWN
Classifier: Programming Language :: Python :: 3
Classifier: Operating System :: Unix
Classifier: Development Status :: 3 - Alpha
Classifier: Topic :: System :: Monitoring
Classifier: License :: OSI Approved :: MIT License
Requires-Python: ~=3.6
Requires-Dist: asynctest (>=0.12.2)
Requires-Dist: ipython (>=6.5.0)
Requires-Dist: ipython-genutils (>=0.2.0)
Requires-Dist: matplotlib (>=2.2.2)
Requires-Dist: numpy (>=1.13.3)
Requires-Dist: pandas (>=0.23.4)
Requires-Dist: pylint (>=2.1.1)
Requires-Dist: PyQt5 (>=5.11.2)
Requires-Dist: PyQt5-sip (>=4.19.12)
Requires-Dist: pyqtgraph (>=0.10.0)
Requires-Dist: pytest (>=3.7.1)
Requires-Dist: pytest-cov (>=2.5.1)
Requires-Dist: scipy (>=0.19.1)
